cassettedeck/__init__.py
cassettedeck/cassette.py
cassettedeck/deck.py
cassettedeck/request.py
cassettedeck/service.py
cassettedeck/store.py
cassettedeck/vcr.py
cassettedeck/tests/__init__.py
cassettedeck/tests/conftest.py
cassettedeck/tests/fixtures.py
cassettedeck/tests/test_vcr.py
cassettedeck/tests/test_works.py
cassettedeck-2.2.0.dist-info/METADATA
cassettedeck-2.2.0.dist-info/WHEEL
cassettedeck-2.2.0.dist-info/top_level.txt
cassettedeck-2.2.0.dist-info/zip-safe
cassettedeck-2.2.0.dist-info/RECORD
